{"version":"0.4","title":"Katka Logistics \u2013 About Us Our partners logo section","type":"section","content":[{"id":"1e6b59ee","settings":{"background_background":"classic","background_color":"#2b9ee5","padding":{"unit":"px","top":"0","right":"0","bottom":"0","left":"0","isLinked":false}},"elements":[{"id":"51e6a0b8","settings":{"_column_size":100},"elements":[{"id":"2e0af22a","settings":[],"elements":[{"id":"562bac74","settings":{"_column_size":100,"_inline_size":null},"elements":[{"id":"b487600","settings":{"title":"our partners","align":"center","title_color":"#ffffff","typography_typography":"custom","typography_font_size":{"unit":"px","size":44},"typography_text_transform":"uppercase","_margin":{"unit":"px","top":"0","right":"0","bottom":"0","left":"0","isLinked":false},"_padding":{"unit":"px","top":"10","right":"0","bottom":"10","left":"0","isLinked":false},"typography_font_size_mobile":{"unit":"px","size":40}},"elements":[],"isInner":false,"widgetType":"heading","elType":"widget"},{"id":"65c2e72c","settings":{"weight":{"unit":"px","size":3},"color":"#ffffff","width":{"unit":"%","size":15},"align":"center","_z_index":0},"elements":[],"isInner":false,"widgetType":"divider","elType":"widget"}],"isInner":true,"elType":"column"}],"isInner":true,"elType":"section"},{"id":"7f791564","settings":{"gap":"no","content_position":"middle","padding":{"unit":"px","top":"0","right":"0","bottom":"0","left":"0","isLinked":true}},"elements":[{"id":"b90a027","settings":{"_column_size":100,"_inline_size":null},"elements":[{"id":"3d9d9d1","settings":{"wp_gallery":[{"id":832,"url":"https:\/\/katka.elementortemplatepack.com\/wp-content\/uploads\/2018\/04\/air-logo-w-2.png"},{"id":833,"url":"https:\/\/katka.elementortemplatepack.com\/wp-content\/uploads\/2018\/04\/air-logo-w-3.png"},{"id":834,"url":"https:\/\/katka.elementortemplatepack.com\/wp-content\/uploads\/2018\/04\/air-logo-w-4.png"},{"id":835,"url":"https:\/\/katka.elementortemplatepack.com\/wp-content\/uploads\/2018\/04\/air-logo-w.png"}],"gallery_columns":"4","gallery_link":"none","gallery_display_caption":"none"},"elements":[],"isInner":false,"widgetType":"image-gallery","elType":"widget"}],"isInner":true,"elType":"column"}],"isInner":true,"elType":"section"}],"isInner":false,"elType":"column"}],"isInner":false,"elType":"section"}]}