{"version":"0.4","title":"elementor features section template 16","type":"section","content":[{"id":"5b3c025c","settings":{"content_position":"middle","background_background":"classic","background_color":"#ffffff","padding":{"unit":"px","top":"100","right":"15","bottom":"100","left":"15","isLinked":false}},"elements":[{"id":"df4e3a","settings":{"_column_size":100,"margin":{"unit":"px","top":"0","right":"0","bottom":"0","left":"0","isLinked":false},"padding":{"unit":"px","top":"0","right":"0","bottom":"0","left":"0","isLinked":false}},"elements":[{"id":"2d9a67f1","settings":{"title":"Katka Elementor Template Pack","align":"center","title_color":"#000000","typography_typography":"custom","typography_font_size":{"unit":"px","size":54},"typography_font_weight":"600","typography_font_size_mobile":{"unit":"px","size":36}},"elements":[],"isInner":false,"widgetType":"heading","elType":"widget"},{"id":"1a801fe5","settings":{"text":"Learn more","align":"center","icon":"fa fa-chevron-right","icon_align":"right","icon_indent":{"unit":"px","size":10},"typography_typography":"custom","typography_font_size":{"unit":"px","size":16},"button_text_color":"#325fe5","background_color":"rgba(0,0,0,0)","_padding":{"unit":"px","top":"0","right":"0","bottom":"35","left":"0","isLinked":false}},"elements":[],"isInner":false,"widgetType":"button","elType":"widget"},{"id":"d03056a","settings":{"structure":"40"},"elements":[{"id":"58add5b3","settings":{"_column_size":25,"_inline_size":null,"padding":{"unit":"px","top":"20","right":"20","bottom":"20","left":"20","isLinked":true}},"elements":[{"id":"5c8f9bf6","settings":{"image":{"id":33,"url":"https:\/\/katka.elementortemplatepack.com\/wp-content\/uploads\/2017\/11\/services1.jpg"},"image_size":"custom","image_custom_dimension":{"width":"400","height":"400"}},"elements":[],"isInner":false,"widgetType":"image","elType":"widget"},{"id":"5f911549","settings":{"title":"Feature One","header_size":"h3","align":"center","align_mobile":"center","title_color":"#000000","typography_typography":"custom","typography_font_size":{"unit":"px","size":32},"typography_font_size_tablet":{"unit":"px","size":28},"typography_font_size_mobile":{"unit":"px","size":32},"typography_font_weight":"600"},"elements":[],"isInner":false,"widgetType":"heading","elType":"widget"}],"isInner":true,"elType":"column"},{"id":"394648b8","settings":{"_column_size":25,"_inline_size":null,"padding":{"unit":"px","top":"20","right":"20","bottom":"20","left":"20","isLinked":true}},"elements":[{"id":"5fa99f05","settings":{"image":{"id":34,"url":"https:\/\/katka.elementortemplatepack.com\/wp-content\/uploads\/2017\/11\/services5b.jpg"},"image_size":"custom","image_custom_dimension":{"width":"400","height":"400"}},"elements":[],"isInner":false,"widgetType":"image","elType":"widget"},{"id":"1855964c","settings":{"title":"Feature Two","header_size":"h3","align":"center","align_mobile":"center","title_color":"#000000","typography_typography":"custom","typography_font_size":{"unit":"px","size":32},"typography_font_size_tablet":{"unit":"px","size":28},"typography_font_size_mobile":{"unit":"px","size":32},"typography_font_weight":"600"},"elements":[],"isInner":false,"widgetType":"heading","elType":"widget"}],"isInner":true,"elType":"column"},{"id":"bf6e8c8","settings":{"_column_size":25,"_inline_size":null,"padding":{"unit":"px","top":"20","right":"20","bottom":"20","left":"20","isLinked":true}},"elements":[{"id":"1a736041","settings":{"image":{"id":35,"url":"https:\/\/katka.elementortemplatepack.com\/wp-content\/uploads\/2017\/11\/services6.jpg"},"image_size":"custom","image_custom_dimension":{"width":"400","height":"400"}},"elements":[],"isInner":false,"widgetType":"image","elType":"widget"},{"id":"69ddee94","settings":{"title":"Feature Three","header_size":"h3","align":"center","align_mobile":"center","title_color":"#000000","typography_typography":"custom","typography_font_size":{"unit":"px","size":32},"typography_font_size_tablet":{"unit":"px","size":28},"typography_font_size_mobile":{"unit":"px","size":32},"typography_font_weight":"600"},"elements":[],"isInner":false,"widgetType":"heading","elType":"widget"}],"isInner":true,"elType":"column"},{"id":"2a417c4","settings":{"_column_size":25,"_inline_size":null,"padding":{"unit":"px","top":"20","right":"20","bottom":"20","left":"20","isLinked":true}},"elements":[{"id":"190fa3fd","settings":{"image":{"id":36,"url":"https:\/\/katka.elementortemplatepack.com\/wp-content\/uploads\/2017\/11\/services4.jpg"},"image_size":"custom","image_custom_dimension":{"width":"400","height":"400"}},"elements":[],"isInner":false,"widgetType":"image","elType":"widget"},{"id":"6ee60133","settings":{"title":"Feature Four","header_size":"h3","align":"center","align_mobile":"center","title_color":"#000000","typography_typography":"custom","typography_font_size":{"unit":"px","size":32},"typography_font_size_tablet":{"unit":"px","size":28},"typography_font_size_mobile":{"unit":"px","size":32},"typography_font_weight":"600"},"elements":[],"isInner":false,"widgetType":"heading","elType":"widget"}],"isInner":true,"elType":"column"}],"isInner":true,"elType":"section"}],"isInner":false,"elType":"column"}],"isInner":false,"elType":"section"}]}