{"version":"0.4","title":"elementor footer template 4","type":"section","content":[{"id":"3c878437","settings":{"content_position":"middle","structure":"30","background_background":"classic","background_color":"#ffffff","margin":{"unit":"px","top":"0","right":0,"bottom":"0","left":0,"isLinked":true},"padding":{"unit":"px","top":"20","right":"25","bottom":"20","left":"25","isLinked":false},"padding_tablet":{"unit":"px","top":"25","right":"0","bottom":"25","left":"0","isLinked":false}},"elements":[{"id":"cecf24b","settings":{"_column_size":33,"_inline_size":12.484,"_inline_size_tablet":25},"elements":[{"id":"38126d6f","settings":{"image":{"id":42,"url":"https:\/\/katka.elementortemplatepack.com\/wp-content\/uploads\/2017\/11\/wpress-zone-logo.jpg"},"image_size":"custom","image_custom_dimension":{"width":"","height":"50"},"align_mobile":"center"},"elements":[],"isInner":false,"widgetType":"image","elType":"widget"}],"isInner":false,"elType":"column"},{"id":"583e5e39","settings":{"_column_size":33,"_inline_size":67.512,"_inline_size_tablet":50,"space_between_widgets":0},"elements":[{"id":"6b97304","settings":{"title":"\u00a9 2017 WPress.zone","header_size":"div","align":"center","align_mobile":"center","title_color":"#000000","typography_typography":"custom","typography_font_size":{"unit":"px","size":18},"typography_font_size_tablet":{"unit":"px","size":18}},"elements":[],"isInner":false,"widgetType":"heading","elType":"widget"}],"isInner":false,"elType":"column"},{"id":"3845b8c0","settings":{"_column_size":33,"_inline_size":20,"_inline_size_tablet":25},"elements":[{"id":"30a66760","settings":{"social_icon_list":[{"social":"fa fa-facebook","_id":"vn9og5j","link":{"url":"","is_external":"true","nofollow":""}},{"social":"fa fa-twitter","_id":"9olm3ux","link":{"url":"","is_external":"true","nofollow":""}},{"social":"fa fa-google-plus","_id":"xxhjsib","link":{"url":"","is_external":"true","nofollow":""}},{"social":"fa fa-instagram","link":{"url":"","is_external":"true","nofollow":""},"_id":"gk5gtv5"}],"shape":"circle","icon_color":"custom","icon_primary_color":"rgba(255,255,255,0)","icon_secondary_color":"#325fe5","icon_size":{"unit":"px","size":20},"icon_spacing":{"unit":"px","size":0},"hover_animation":"grow"},"elements":[],"isInner":false,"widgetType":"social-icons","elType":"widget"}],"isInner":false,"elType":"column"}],"isInner":false,"elType":"section"}]}