{"version":"0.4","title":"Katka Finance \u2013 Home page hero header","type":"section","content":[{"id":"566a04a7","settings":{"height":"full","content_position":"middle","background_background":"classic","background_image":{"id":546,"url":"https:\/\/katka.elementortemplatepack.com\/wp-content\/uploads\/2018\/02\/london-2427851_1920.png"},"background_position":"top center","background_repeat":"no-repeat","background_size":"cover","background_overlay_background":"classic","background_overlay_color":"#ffffff","background_overlay_opacity":{"unit":"px","size":0.92},"padding":{"unit":"px","top":"0","right":"0","bottom":"0","left":"0","isLinked":false},"background_attachment":"fixed","padding_mobile":{"unit":"px","top":"150","right":"10","bottom":"25","left":"10","isLinked":false}},"elements":[{"id":"70ef021a","settings":{"_column_size":100,"_inline_size":null,"_inline_size_tablet":99,"content_position":"center"},"elements":[{"id":"ed8c1c5","settings":{"title":"WPress.zone Finance","title_color":"#163651","header_size":"h1","align":"center","align_tablet":"center","typography_typography":"custom","typography_font_size":{"unit":"px","size":84},"typography_font_size_mobile":{"unit":"px","size":48},"typography_font_weight":"600","text_shadow_text_shadow":{"horizontal":3,"vertical":2,"blur":0,"color":"rgba(0,165,223,0.48)"},"typography_font_size_tablet":{"unit":"px","size":50},"_padding_tablet":{"unit":"px","top":"0","right":"0","bottom":"0","left":"0","isLinked":true},"typography_font_family":"Quattrocento"},"elements":[],"isInner":false,"widgetType":"heading","elType":"widget"},{"id":"19bdef64","settings":{"editor":"<p>Lorem ipsum dolor sit amet, consectetur adipiscing elit. \u00a0<\/p>","align_tablet":"center","_padding":{"unit":"px","top":"5","right":"125","bottom":"0","left":"125","isLinked":false},"align":"center","text_color":"#163651","typography_typography":"custom","typography_font_size":{"unit":"px","size":24},"_padding_mobile":{"unit":"px","top":"10","right":"10","bottom":"10","left":"10","isLinked":true},"typography_font_family":"Fanwood Text","typography_font_weight":"600"},"elements":[],"isInner":false,"widgetType":"text-editor","elType":"widget"},{"id":"53f5ff50","settings":{"padding":{"unit":"px","top":"0","right":"0","bottom":"0","left":"0","isLinked":true}},"elements":[{"id":"401c1d77","settings":{"_column_size":100,"_inline_size":null,"padding_mobile":{"unit":"px","top":"0","right":"5","bottom":"0","left":"0","isLinked":false},"content_position":"center"},"elements":[{"id":"30c6297f","settings":{"text":"contact us","align":"center","typography_typography":"custom","typography_text_transform":"uppercase","_padding":{"unit":"px","top":"5","right":"5","bottom":"5","left":"5","isLinked":true},"background_color":"#163651","hover_color":"#163651","button_background_hover_color":"rgba(255,255,255,0.5)","border_border":"solid","border_width":{"unit":"px","top":"1","right":"1","bottom":"1","left":"1","isLinked":true},"border_color":"#163651","_padding_mobile":{"unit":"px","top":"0","right":"0","bottom":"0","left":"0","isLinked":false},"align_tablet":"center","align_mobile":"center","typography_font_size":{"unit":"px","size":22},"typography_font_family":"Fanwood Text","typography_font_weight":"600"},"elements":[],"isInner":false,"widgetType":"button","elType":"widget"}],"isInner":true,"elType":"column"}],"isInner":true,"elType":"section"}],"isInner":false,"elType":"column"}],"isInner":false,"elType":"section"}]}